PYTypeValidator/__init__.py
pytypevalidator-0.1.0.dist-info/entry_points.txt
pytypevalidator-0.1.0.dist-info/LICENSE.txt
pytypevalidator-0.1.0.dist-info/METADATA
pytypevalidator-0.1.0.dist-info/WHEEL
pytypevalidator-0.1.0.dist-info/RECORD
