Metadata-Version: 2.3
Name: PYTypeValidator
Version: 0.1.0
Summary: A simple utility class to validate and convert types in Python
License: MIT
Author: Ch Ahmed ahmedchouikh78@gmail.com
Requires-Python: >=3.7,<4.0
Classifier: License :: OSI Approved :: MIT License
Classifier: Programming Language :: Python :: 3
Classifier: Programming Language :: Python :: 3.7
Classifier: Programming Language :: Python :: 3.8
Classifier: Programming Language :: Python :: 3.9
Classifier: Programming Language :: Python :: 3.10
Classifier: Programming Language :: Python :: 3.11
Classifier: Programming Language :: Python :: 3.12
Classifier: Programming Language :: Python :: 3.13
Project-URL: Homepage, https://github.com/Ahmed775c6/TypeValidatorv1
Project-URL: Repository, https://github.com/Ahmed775c6/TypeValidatorv1
